ofxstatement_al_bank-0.2.1-py3.8-nspkg.pth
ofxstatement/plugins/al_bank.py
ofxstatement_al_bank-0.2.1.dist-info/LICENSE.txt
ofxstatement_al_bank-0.2.1.dist-info/METADATA
ofxstatement_al_bank-0.2.1.dist-info/WHEEL
ofxstatement_al_bank-0.2.1.dist-info/entry_points.txt
ofxstatement_al_bank-0.2.1.dist-info/namespace_packages.txt
ofxstatement_al_bank-0.2.1.dist-info/top_level.txt
ofxstatement_al_bank-0.2.1.dist-info/zip-safe
ofxstatement_al_bank-0.2.1.dist-info/RECORD
