Metadata-Version: 2.1
Name: ofxstatement-al-bank
Version: 0.2.1
Summary: Arbejdernes Landsbank plugin for ofxstatement
Home-page: https://github.com/lbschenkel/ofxstatement-al_bank
Author: Leonardo Brondani Schenkel
Author-email: leonardo@schenkel.net
License: GPLv3
Keywords: ofx,banking,statement
Platform: UNKNOWN
Classifier: Development Status :: 4 - Beta
Classifier: Programming Language :: Python :: 3
Classifier: Natural Language :: English
Classifier: Topic :: Office/Business :: Financial :: Accounting
Classifier: Topic :: Utilities
Classifier: Environment :: Console
Classifier: Operating System :: OS Independent
Classifier: License :: OSI Approved :: GNU General Public License v3 (GPLv3)
Requires-Dist: ofxstatement
